disperse/__init__.py
disperse/__main__.py
disperse/cargo.py
disperse/config.py
disperse/config_pb2.py
disperse/github.py
disperse/launchpad.py
disperse/news_file.py
disperse/python.py
disperse-0.0.7.dist-info/LICENSE
disperse-0.0.7.dist-info/METADATA
disperse-0.0.7.dist-info/WHEEL
disperse-0.0.7.dist-info/entry_points.txt
disperse-0.0.7.dist-info/top_level.txt
disperse-0.0.7.dist-info/RECORD
