Metadata-Version: 2.1
Name: disperse
Version: 0.0.7
Summary: automation for creation of releases
Author-email: Jelmer Vernooij <jelmer@jelmer.uk>
Project-URL: Homepage, https://github.com/jelmer/disperse
Project-URL: Repository, https://github.com/jelmer/disperse.git
License-File: LICENSE
Requires-Dist: breezy (>=3.3.0.dev.0)
Requires-Dist: protobuf (>=2.4)
Requires-Dist: pygithub
Requires-Dist: launchpadlib
Requires-Dist: silver-platter (>=0.5.2)
Requires-Dist: build
Requires-Dist: prometheus-client (>=0.15)
Requires-Dist: mypy-protobuf
Requires-Dist: toml
